bodo_platform_utils/__init__.py
bodo_platform_utils/_version.py
bodo_platform_utils/bodosqlwrapper.py
bodo_platform_utils/catalog.py
bodo_platform_utils/config.py
bodo_platform_utils/secrets.py
bodo_platform_utils/utils_types.py
bodo_platform_utils-0.1.2.dist-info/LICENSE
bodo_platform_utils-0.1.2.dist-info/METADATA
bodo_platform_utils-0.1.2.dist-info/WHEEL
bodo_platform_utils-0.1.2.dist-info/top_level.txt
bodo_platform_utils-0.1.2.dist-info/RECORD
