Metadata-Version: 2.1
Name: bodo-platform-utils
Version: 0.1.2
Summary: This is package contains utility functions to retrieve data from Cloud Providers for platform
Home-page: https://github.com/Bodo-inc/bodo-platform-utils
Author: Bodo Inc
Author-email: noreply@bodo.ai
License: UNKNOWN
Platform: UNKNOWN
Classifier: Programming Language :: Python :: 3
Classifier: License :: OSI Approved :: MIT License
Classifier: Operating System :: OS Independent
License-File: LICENSE
Requires-Dist: azure-identity >=1.12.0
Requires-Dist: azure-keyvault-secrets >=4.7.0
Requires-Dist: boto3 >=1.33.0
Requires-Dist: botocore >=1.33.0
Requires-Dist: jmespath >=1.0.0
Requires-Dist: python-dateutil >=2.8.2
Requires-Dist: s3transfer >=0.10.0
Requires-Dist: six >=1.16.0
Requires-Dist: urllib3 >=1.26.9
Requires-Dist: mpi4py ==3.1.5
Requires-Dist: requests
Requires-Dist: cachetools >=5.3.0
